Metadata-Version: 2.1
Name: odoo13-addon-account-due-list-payment-mode
Version: 13.0.2.0.0
Summary: Payment Due List Payment Mode
Home-page: https://github.com/OCA/account-payment
Author: Obertix Free Solutions, Tecnativa, Odoo Community Association (OCA),
Author-email: support@odoo-community.org
License: AGPL-3
Platform: UNKNOWN
Classifier: Programming Language :: Python
Classifier: Framework :: Odoo
Classifier: License :: OSI Approved :: GNU Affero General Public License v3
Requires-Python: >=3.5
Requires-Dist: odoo13-addon-account-due-list
Requires-Dist: odoo13-addon-account-payment-partner
Requires-Dist: odoo (<13.1dev,>=13.0a)
